readonly_fs_tools/glob.py
readonly_fs_tools/sandbox.py
readonly_fs_tools/view.py
readonly_fs_tools/budget.py
readonly_fs_tools/_internal/regex_searcher.py
readonly_fs_tools/_internal/file_reader.py
readonly_fs_tools/_internal/__init__.py
readonly_fs_tools/_internal/path_enumerator.py
readonly_fs_tools/grep.py
readonly_fs_tools/common.py
readonly_fs_tools/__init__.py
readonly_fs_tools-0.2.0.dist-info/WHEEL
readonly_fs_tools-0.2.0.dist-info/METADATA
readonly_fs_tools-0.2.0.dist-info/RECORD
